{
  "rank": 0,
  "current_epoch": 100,
  "current_iteration": 2400,
  "total_epochs": 100,
  "total_iterations": 24,
  "epoch": 100,
  "start_ts": 1696444260,
  "total_time": "0:13:30",
  "best_metric": 0.8215821385383606,
  "train": {
    "metrics": {
      "train_mean_dice": 0.6063033938407898
    },
    "key_metric_name": "train_mean_dice",
    "best_metric": 0.8294763565063477,
    "best_metric_epoch": 81
  },
  "eval": {
    "metrics": {
      "val_mean_dice": 0.7490074038505554
    },
    "key_metric_name": "val_mean_dice",
    "best_metric": 0.8215821385383606,
    "best_metric_epoch": 41
  }
}